flask_cfaccess.py
flask_cfaccess-0.1.1.dist-info/LICENSE
flask_cfaccess-0.1.1.dist-info/METADATA
flask_cfaccess-0.1.1.dist-info/WHEEL
flask_cfaccess-0.1.1.dist-info/top_level.txt
flask_cfaccess-0.1.1.dist-info/RECORD
