Metadata-Version: 2.1
Name: flask-cfaccess
Version: 0.1.1
Summary: Zero Trust Access with Cloudflare Access for Flask applications.
Author-email: Michael de Villiers <michael@devilears.co.za>
Maintainer-email: Michael de Villiers <michael@devilears.co.za>
License: MIT
Project-URL: Documentation, https://flask-cfaccess.readthedocs.io/
Project-URL: Changes, https://flask-cfaccess.readthedocs.io/changes/
Project-URL: Source Code, https://github.com/COUR4G3/flask-cfaccess/
Project-URL: Issue Tracker, https://github.com/COUR4G3/hacksaw/flask-cfaccess/
Classifier: Development Status :: 4 - Beta
Classifier: Environment :: Web Environment
Classifier: Intended Audience :: Developers
Classifier: License :: OSI Approved :: MIT License
Classifier: Operating System :: OS Independent
Classifier: Programming Language :: Python
Classifier: Topic :: Internet :: WWW/HTTP :: Dynamic Content
Requires-Python: >=3.8
License-File: LICENSE
Requires-Dist: flask (~=2.2.3)
Requires-Dist: pyjwt (~=2.6.0)
Requires-Dist: requests (~=2.28.2)
Provides-Extra: dev
Requires-Dist: bandit ; extra == 'dev'
Requires-Dist: black ; extra == 'dev'
Requires-Dist: flake8 ; extra == 'dev'
Requires-Dist: isort ; extra == 'dev'
Requires-Dist: pre-commit (~=2.21.0) ; extra == 'dev'
Requires-Dist: pydocstyle ; extra == 'dev'
Provides-Extra: docs
Requires-Dist: m2r2 (~=0.3.3) ; extra == 'docs'
Requires-Dist: setuptools-scm (~=7.1.0) ; extra == 'docs'
Requires-Dist: sphinx (~=6.1.3) ; extra == 'docs'
Requires-Dist: sphinx-issues (~=3.0.1) ; extra == 'docs'
Requires-Dist: sphinx-prompt (~=1.6.0) ; extra == 'docs'
Provides-Extra: flask-login
Requires-Dist: flask-login (~=0.6.2) ; extra == 'flask-login'
Provides-Extra: test
Requires-Dist: pytest (~=7.2.0) ; extra == 'test'
Requires-Dist: pytest-cov (~=4.0.0) ; extra == 'test'
Requires-Dist: pytest-mock (~=3.10.0) ; extra == 'test'
Requires-Dist: pytest-skip-slow (==0.0.3) ; extra == 'test'
Requires-Dist: responses (~=0.23.1) ; extra == 'test'
